[
  {
    "id": "1",
    "nama": "Single Beef",
    "detail": "Burger berisi beef",
    "kategori": "snack",
    "harga": 19000,
    "kedai": "Burger Bulgel",
    "rate": 4,
    "foto": "https://foodmenu-api.herokuapp.com/images/single_beef.jpg"
  },
  {
    "id": "2",
    "nama": "Single Beef Cheese",
    "detail": "Burger berisi beef + Keju",
    "kategori": "snack",
    "harga": 25000,
    "kedai": "Burger Bulgel",
    "rate": 4,
    "foto": "https://foodmenu-api.herokuapp.com/images/single_beef_cheese.jpg"
  },
  {
    "id": "3",
    "nama": "Double Beef",
    "detail": "Burger dengan double beef",
    "kategori": "snack",
    "harga": 30000,
    "kedai": "Burger Bulgel",
    "rate": 4,
    "foto": "https://foodmenu-api.herokuapp.com/images/double_beef.png"
  },

  {
    "id": "4",
    "nama": "Double Beef Cheese",
    "detail": "Burger dengan double beef dan cheese",
    "kategori": "snack",
    "kedai": "Burger Bulgel",
    "harga": 35000,
    "rate": 4,
    "foto": "https://foodmenu-api.herokuapp.com/images/double_beef_cheese.jpg"
  },
  {
    "id": "5",
    "nama": "Chocomaltine Keju",
    "detail": "Roti bakar dengan Chocomaltine dan Keju",
    "kategori": "snack",
    "kedai": "Roti Bakar bandung",
    "harga": 20000,
    "rate": 4.1,
    "foto": "https://foodmenu-api.herokuapp.com/images/Bakar_Chocomaltine_Keju.jpg"
  },
  {
    "id": "6",
    "nama": "Cheese Red Velvet",
    "detail": "Roti bakar dengan Cheese dan Red Velvet",
    "kategori": "snack",
    "kedai": "Roti Bakar bandung",
    "harga": 18000,
    "rate": 4,
    "foto": "https://foodmenu-api.herokuapp.com/images/Bakar_Red.jpg"
  },

  {
    "id": "7",
    "nama": "Milo Cream Cheese",
    "detail": "Roti Bakar dengan Milo Cream dan Cheese",
    "kategori": "snack",
    "kedai": "Roti Bakar bandung",
    "harga": 18000,
    "rate": 4,
    "foto": "https://foodmenu-api.herokuapp.com/images/Bakar_Milo.jpg"
  },
  {
    "id": "8",
    "nama": "Chocomaltine",
    "detail": "Roti Bakar degan Chocomaltine",
    "kategori": "snack",
    "kedai": "Roti Bakar bandung",
    "harga": 16000,
    "rate": 4,
    "foto": "https://foodmenu-api.herokuapp.com/images/Bakar_Chocomaltine.jpg"
  },
  {
    "id": "9",
    "nama": "Choco Crunchy",
    "detail": "Roti Bakar dengan Choco Crunchy",
    "kategori": "snack",
    "kedai": "Roti Bakar bandung",
    "harga": 15000,
    "rate": 3.8,
    "foto": "https://foodmenu-api.herokuapp.com/images/Bakar_Coklat.jpg"
  },
  {
    "id": "10",
    "nama": "Coklat Keju",
    "detail": "Roti Bakar Coklat Keju",
    "kategori": "snack",
    "kedai": "Roti Bakar bandung",
    "harga": 15000,
    "rate": 4.4,
    "foto": "https://foodmenu-api.herokuapp.com/images/Bakar_Coklat_Keju.jpg"
  },
  {
    "id": "11",
    "nama": "Tiramisu",
    "detail": "Roti Bakar Tiramisu",
    "kategori": "snack",
    "kedai": "Roti Bakar bandung",
    "harga": 15000,
    "rate": 4,
    "foto": "https://foodmenu-api.herokuapp.com/images/Bakar_Tiramisu.jpg"
  },
  {
    "id": "12",
    "nama": "Coklat Kacang",
    "detail": "Roti Bakar Coklat Kacang",
    "kategori": "snack",
    "harga": 15000,
    "rate": 4,
    "foto": "https://foodmenu-api.herokuapp.com/images/Bakar_Coklat.jpg"
  },
  {
    "id": "13",
    "nama": "Cream Cheese",
    "detail": "Roti Bakar dengan Cream Cheese",
    "kategori": "snack",
    "kedai": "Roti Bakar bandung",
    "harga": 15000,
    "rate": 4,
    "foto": "https://foodmenu-api.herokuapp.com/images/Bakar_Keju.jpg"
  },
  {
    "id": "14",
    "nama": "Srikaya",
    "detail": "Roti Bakar Srikaya",
    "kategori": "snack",
    "kedai": "Roti Bakar bandung",
    "harga": 15000,
    "rate": 4,
    "foto": "https://foodmenu-api.herokuapp.com/images/noimage.png"
  },
  {
    "id": "15",
    "nama": "Chocolate Mint",
    "detail": "Minuman segar dengan Chocolate Min",
    "kategori": "drink",
    "harga": 12000,
    "kedai": "Manja Artisan Cheese Tea",
    "rate": 4,
    "foto": "https://foodmenu-api.herokuapp.com/images/Coklat_Mint.png"
  },
  {
    "id": "16",
    "nama": "Kebab Durian Original",
    "detail": "Kebab Toping Durian",
    "kategori": "snack",
    "kedai": "Kebab Durian Becek",
    "harga": 15000,
    "rate": 4.3,
    "foto": "https://foodmenu-api.herokuapp.com/images/kebab_ori.jpg"
  },
  {
    "id": "17",
    "nama": "Kebab Durian Oreo",
    "detail": "Kebab Toping Durian + Oreo",
    "kategori": "snack",
    "kedai": "Kebab Durian Becek",
    "harga": 17000,
    "rate": 4.1,
    "foto": "https://foodmenu-api.herokuapp.com/images/kebab_oreo.jpg"
  },
  {
    "id": "18",
    "nama": "Kebab Durian Ice Cream",
    "detail": "Kebab Durian toping Ice Cream",
    "kategori": "snack",
    "harga": 18000,
    "kedai": "Kebab Durian Becek",
    "rate": 4.3,
    "foto": "https://foodmenu-api.herokuapp.com/images/kebab_icecream.jpg"
  },
  {
    "id": "19",
    "nama": "Kebab Durian Ovaltine",
    "detail": "Kebab dengan toping Durian + Ovaltine",
    "kategori": "snack",
    "harga": 20000,
    "kedai": "Kebab Durian Becek",
    "rate": 4,
    "foto": "https://foodmenu-api.herokuapp.com/images/kebab_ovaltine.jpg"
  },
  {
    "id": "20",
    "nama": "Chocolate Lava",
    "detail": "Minuman segar dengan toping Chocolate Lava",
    "kategori": "drink",
    "harga": 12000,
    "kedai": "Manja Artisan Cheese Tea",
    "rate": 4,
    "foto": "https://foodmenu-api.herokuapp.com/images/Red_Lava.png"
  },
  {
    "id": "21",
    "nama": "Sate Taichan",
    "detail": "Sate Taichan",
    "kategori": "food",
    "harga": 20000,
    "kedai": "Dapur Omah",
    "rate": 4,
    "foto": "https://foodmenu-api.herokuapp.com/images/sate_taichan.jpg"
  },
  {
    "id": "22",
    "nama": "Kebab Daging/Sosis",
    "detail": "Kebab dengan toping  Daging/Sosis",
    "kategori": "snack",
    "harga": 13000,
    "kedai": "Dapur Omah",
    "rate": 3.8,
    "foto": "https://foodmenu-api.herokuapp.com/images/kebab_daging.jpg"
  },
  {
    "id": "23",
    "nama": "Nasi Ayam Kremes Goreng/bakar",
    "detail": "Nasi + Ayam Kremes Goren/Bakar",
    "kategori": "food",
    "harga": 20000,
    "kedai": "Dapur Omah",
    "rate": 4.1,
    "foto": "https://foodmenu-api.herokuapp.com/images/ayam_kremes.jpg"
  },
  {
    "id": "24",
    "nama": "Nasi Ayam Goreng Kalasan",
    "detail": "Nasi + Ayam goreng kalasan",
    "kategori": "food",
    "harga": 20000,
    "kedai": "Dapur Omah",
    "rate": 4,
    "foto": "https://foodmenu-api.herokuapp.com/images/ayam_kalasan.jpg"
  },
  {
    "id": "25",
    "nama": "Kuta Subbaem",
    "detail": "Minuman segar ala bali",
    "kategori": "drink",
    "harga": 12000,
    "kedai": "Manja Artisan Cheese Tea",
    "rate": 4,
    "foto": "https://foodmenu-api.herokuapp.com/images/kuta.png"
  },
  {
    "id": "26",
    "nama": "Camouflage",
    "detail": "Minaman segar ala california",
    "kategori": "drink",
    "harga": 12000,
    "kedai": "Manja Artisan Cheese Tea",
    "rate": 4,
    "foto": "https://foodmenu-api.herokuapp.com/images/camuf.png"
  },
  {
    "id": "27",
    "nama": "Summer Party",
    "detail": "Minuman suasana musim panas",
    "kategori": "drink",
    "harga": 12000,
    "kedai": "Manja Artisan Cheese Tea",
    "rate": 4,
    "foto": "https://foodmenu-api.herokuapp.com/images/Summer.png"
  },
  {
    "id": "28",
    "nama": "Coffee Unicorn",
    "detail": "Minuman segar kopi anak muda",
    "kategori": "drink",
    "harga": 12000,
    "kedai": "Manja Artisan Cheese Tea",
    "rate": 4,
    "foto": "https://foodmenu-api.herokuapp.com/images/coffe.png"
  },
  {
    "id": "29",
    "nama": "Red Velvet",
    "detail": "......",
    "kategori": "drink",
    "harga": 12000,
    "kedai": "Manja Artisan Cheese Tea",
    "rate": 3.9,
    "foto": "https://foodmenu-api.herokuapp.com/images/Red_Velvet.png"
  }
]
